nervaluate/__init__.py
nervaluate/entities.py
nervaluate/evaluator.py
nervaluate/loaders.py
nervaluate/strategies.py
nervaluate/utils.py
nervaluate-1.1.0.dist-info/licenses/LICENSE
nervaluate-1.1.0.dist-info/METADATA
nervaluate-1.1.0.dist-info/WHEEL
nervaluate-1.1.0.dist-info/top_level.txt
nervaluate-1.1.0.dist-info/RECORD
