Metadata-Version: 2.4
Name: nervaluate
Version: 1.1.0
Summary: NER evaluation considering partial match scoring
Author: David S. Batista, Matthew Upson
License: MIT License
Project-URL: Homepage, https://github.com/MantisAI/nervaluate
Project-URL: Bug Tracker, https://github.com/MantisAI/nervaluate/issues
Keywords: named-entity-recognition,ner,evaluation-metrics,partial-match-scoring,nlp
Classifier: Programming Language :: Python :: 3
Classifier: Operating System :: OS Independent
Requires-Python: >=3.11
License-File: LICENSE
Provides-Extra: dev
Requires-Dist: black>=25.1.0; extra == "dev"
Requires-Dist: coverage>=7.8.0; extra == "dev"
Requires-Dist: gitchangelog; extra == "dev"
Requires-Dist: mypy>=1.15.0; extra == "dev"
Requires-Dist: pre-commit==3.3.1; extra == "dev"
Requires-Dist: pylint>=3.3.7; extra == "dev"
Requires-Dist: pytest>=8.3.5; extra == "dev"
Requires-Dist: pytest-cov>=6.1.1; extra == "dev"
Dynamic: license-file
